smpr3d/__init__.py
smpr3d/_nbdev.py
smpr3d/algorithm.py
smpr3d/core.py
smpr3d/functional.py
smpr3d/kernels.py
smpr3d/operators.py
smpr3d/setup.py
smpr3d/torch_imports.py
smpr3d/util.py
smpr3d-0.0.3.dist-info/LICENSE
smpr3d-0.0.3.dist-info/METADATA
smpr3d-0.0.3.dist-info/WHEEL
smpr3d-0.0.3.dist-info/entry_points.txt
smpr3d-0.0.3.dist-info/top_level.txt
smpr3d-0.0.3.dist-info/RECORD
