Metadata-Version: 2.1
Name: smpr3d
Version: 0.0.3
Summary: smpr3d is a toolkit for 3D reconstruction from scanning diffraction data
Home-page: https://github.com/s-matrix/smpr3d/tree/master/
Author: Philipp Pelz
Author-email: philipp.pelz@yahoo.de
License: MIT License
Keywords: phase retrieval,optimization,4D-STEM
Platform: UNKNOWN
Classifier: Development Status :: 3 - Alpha
Classifier: Intended Audience :: Developers
Classifier: Natural Language :: English
Classifier: Programming Language :: Python :: 3.6
Classifier: Programming Language :: Python :: 3.7
Classifier: Programming Language :: Python :: 3.8
Classifier: License :: OSI Approved :: MIT License
Requires-Python: >=3.6
Requires-Dist: torchvision
Requires-Dist: psutil
Requires-Dist: matplotlib
Requires-Dist: tifffile
Requires-Dist: jupyterlab
Requires-Dist: ipympl
Requires-Dist: ipywidgets
Requires-Dist: scikit-image
Requires-Dist: numba
Requires-Dist: tensorboard
